LICENSE.txt
MANIFEST.in
README.rst
setup.py
scMet/CVAEmodel.py
scMet/Dataloader.py
scMet/Deconvolution.py
scMet/GenerateData.py
scMet/Main.py
scMet/Simulation.py
scMet/Std_choose.py
scMet/__init__.py
scMet.egg-info/PKG-INFO
scMet.egg-info/SOURCES.txt
scMet.egg-info/dependency_links.txt
scMet.egg-info/requires.txt
scMet.egg-info/top_level.txt