Metadata-Version: 2.1
Name: scMet
Version: 1.0.0
Summary: Fits bulk RNA-seq data using single-cell RNA-seq (scRNA-seq) data, enabling accurate estimation and analysis of gene expression profiles and metabolic flux balance
Home-page: https://github.com/your_username/your_package
Author: Gw yang
Author-email: stu_gwyang@163.com
Requires-Python: >=3.8
License-File: LICENSE.txt
